{
  "limitedTimePost": [
    {
      "id": "1",
      "avatar": "/images/avatar/taeyeon.jpg",
      "account": "taeyeon_ss"
    },
    {
      "id": "2",
      "avatar": "/images/avatar/yoona.jpg",
      "account": "yoona__lim"
    },
    {
      "id": "3",
      "avatar": "/images/avatar/sooyoung.jpg",
      "account": "sooyoungchoi"
    },
    {
      "id": "4",
      "avatar": "/images/avatar/sunny.jpg",
      "account": "515sunnyday"
    },
    {
      "id": "5",
      "avatar": "/images/avatar/yuri.jpg",
      "account": "yulyulk"
    },
    {
      "id": "6",
      "avatar": "/images/avatar/seohyun.jpg",
      "account": "seojuhyun_s"
    },
    {
      "id": "7",
      "avatar": "/images/avatar/hyoyeon.jpg",
      "account": "hyoyeon_x_x"
    },
    {
      "id": "8",
      "avatar": "/images/avatar/tiffany.jpg",
      "account": "tiffanyyoungofficial"
    },
    {
      "id": "9",
      "avatar": "/images/avatar/iu.jpg",
      "account": "dlwlrma"
    },
    {
      "id": "10",
      "avatar": "/images/avatar/enuji.jpg",
      "account": "artist_eunji"
    }
  ]
}
